AGSM/_test.py
AGSM/convert.py
AGSM/convertProperties.py
AGSM/extraction.py
AGSM-0.1.0.dist-info/METADATA
AGSM-0.1.0.dist-info/WHEEL
AGSM-0.1.0.dist-info/top_level.txt
AGSM-0.1.0.dist-info/RECORD
