Metadata-Version: 2.1
Name: AGSM
Version: 0.1.0
Summary: ???
Home-page: https://github.com/YFKS/AGSM
Author: Ayato
Author-email: ayato.yofukashi@gmail.com
Classifier: Programming Language :: Python :: 3
Classifier: License :: OSI Approved :: MIT License
Classifier: Operating System :: OS Independent
Requires-Python: >=3.0
